{
  "version": "1.1.0",
  "url": "https://serlortrademark.github.io/serloplaygames/",
  "notes": "Interfaz simplificada y más coherente, retoque de algunos botones y ajustes visuales y de espaciado en la interfaz.",

  "free_mode_enabled": false,
  "minimum_allowed_version": "2.0.0",
  "block_licensed_users": false,

  "license_plan_name": "1 año",
  "license_price_eur": "7",

  "stripe_url": "https://buy.stripe.com/fZu00b9jhavXgAd9uM93y0",

  "help_url": "https://docs.google.com/forms/d/e/1FAIpQLSd19uy1a_KOiee_vySDFn6GRLwMrAbgI7NV0iwwub8DZdmZog/viewfor"
}